ChangeLog
LICENSE
MANIFEST.in
README.md
README.rst
cmp-version
setup.py
cmp_version/__init__.py
cmp_version.egg-info/PKG-INFO
cmp_version.egg-info/SOURCES.txt
cmp_version.egg-info/dependency_links.txt
cmp_version.egg-info/top_level.txt
doc/cmp_version.html
doc/index.html
tests/runTests.py
tests/cmp_version_Tests/test_Epoch.py
tests/cmp_version_Tests/test_General.py
tests/cmp_version_Tests/test_Release.py