Metadata-Version: 1.2
Name: cmp-version
Version: 3.0.0
Summary: A script and python module to compare version numbers. Use this to compare the version strings of packages, modules, really anything.
Home-page: https://github.com/kata198/cmp_version
Author: Tim Savannah
Author-email: kata198@gmail.com
Maintainer: Tim Savannah
Maintainer-email: kata198@gmail.com
License: Public Domain
Keywords: cmp,version,cmp_version,compare,version,number,package,rpm,commandline,tool,module,release
Platform: UNKNOWN
Classifier: Development Status :: 5 - Production/Stable
Classifier: Programming Language :: Python
Classifier: License :: Public Domain
Classifier: Programming Language :: Python :: 2
Classifier: Programming Language :: Python :: 2
Classifier: Programming Language :: Python :: 2.6
Classifier: Programming Language :: Python :: 2.7
Classifier: Programming Language :: Python :: 3
Classifier: Programming Language :: Python :: 3.3
Classifier: Programming Language :: Python :: 3.4
Classifier: Programming Language :: Python :: 3.5
Classifier: Programming Language :: Python :: 3.6
Classifier: Topic :: Software Development :: Version Control
Classifier: Topic :: Software Development :: Libraries :: Python Modules
